sympair/__init__.py
sympair/magnetic_symmetry.py
sympair/spacegroup.py
sympair/symmetry_pairs.py
sympair/utils.py
sympair-0.1.4.dist-info/licenses/LICENSE
sympair-0.1.4.dist-info/METADATA
sympair-0.1.4.dist-info/WHEEL
sympair-0.1.4.dist-info/top_level.txt
sympair-0.1.4.dist-info/RECORD
